Metadata-Version: 1.0
Name: mal-distributions
Version: 0.1
Summary: Gaussian and Binomial distributions
Home-page: UNKNOWN
Author: Malik Taiwo
Author-email: maliktadelana@gmail.com
License: UNKNOWN
Platform: UNKNOWN
